gge/__init__.py
gge/gge.py
gmail_generator-4.6.1.dist-info/METADATA
gmail_generator-4.6.1.dist-info/WHEEL
gmail_generator-4.6.1.dist-info/top_level.txt
gmail_generator-4.6.1.dist-info/RECORD
